README.md
setup.cfg
setup.py
billplz/__init__.py
billplz/client.py
billplz_python.egg-info/PKG-INFO
billplz_python.egg-info/SOURCES.txt
billplz_python.egg-info/dependency_links.txt
billplz_python.egg-info/top_level.txt
tests/__init__.py
tests/test_billplz.py