Metadata-Version: 1.1
Name: billplz-python
Version: 1.0.1
Summary: Billplz Client Interface
Home-page: https://github.com/mattyc246/billplz-python
Author: Matthew Cross
Author-email: mattyc246@gmail.com
License: MIT
Download-URL: https://github.com/mattyc246/billplz-python/archive/1.0.1.tar.gz
Keywords: billplz,payment,payment gateway
Platform: UNKNOWN
Classifier: Development Status :: 3 - Alpha
Classifier: Intended Audience :: Developers
Classifier: Topic :: Software Development :: Build Tools
Classifier: License :: OSI Approved :: MIT License
Classifier: Programming Language :: Python :: 3
